sageranger/__init__.py
sageranger/attach_image_er.py
sageranger/get_cam_location.py
sageranger/post_cougar_log.py
sageranger/post_event_er.py
sageranger/post_monthly.py
sageranger-1.0.4.dist-info/LICENSE
sageranger-1.0.4.dist-info/METADATA
sageranger-1.0.4.dist-info/WHEEL
sageranger-1.0.4.dist-info/top_level.txt
sageranger-1.0.4.dist-info/RECORD
