Metadata-Version: 2.1
Name: sageranger
Version: 1.0.4
Summary: Package to aide in utilization of Earthranger
Home-page: https://github.com/conservationtechlab/sageranger
Author: Katie Garwood
Author-email: Katie Garwood <kgarwood@sdzwa.org>
License: MIT License
Project-URL: Homepage, https://github.com/conservationtechlab/sageranger
Keywords: feed,reader,tutorial
Classifier: License :: OSI Approved :: MIT License
Classifier: Programming Language :: Python
Classifier: Programming Language :: Python :: 3
Requires-Python: >=3.7
License-File: LICENSE
Requires-Dist: requests
Requires-Dist: datetime
Provides-Extra: dev
